[
  {
    "Type": "ARCPEERQUARTILES",
    "KeyInt": 372029325,
    "Key": 1,
    "RegionSubRegion": "Asia",
    "Industry": "Services",
    "Year": 2020,
    "Ratio": 1.5,
    "Quartile1": 60.0,
    "Quartile2": 70.0,
    "Quartile3": 180.0,
    "Inapplicable_": [],
    "IsDeleted_": false,
    "StatusId_": 1,
    "CreatedBy_": "internalbatchuser",
    "CreatedDate_": "2020-09-03T09:25:03.060341Z",
    "t_": "ArcPeerQuartiles",
    "ContextUserId_": "internalbatchuser"
  },
  {
    "Type": "ARCPEERQUARTILES",
    "KeyInt": 372029328,
    "Key": 2,
    "RegionSubRegion": "Asia",
    "Industry": "services",
    "Year": 2020,
    "Ratio": 1.75,
    "Quartile1": 62.0,
    "Quartile2": 72.0,
    "Quartile3": 182.0,
    "Inapplicable_": [],
    "IsDeleted_": false,
    "StatusId_": 1,
    "CreatedBy_": "internalbatchuser",
    "CreatedDate_": "2020-09-03T09:25:03.085721Z",
    "t_": "ArcPeerQuartiles",
    "ContextUserId_": "internalbatchuser"
  },
  {
    "Type": "ARCPEERQUARTILES",
    "KeyInt": 372029327,
    "Key": 3,
    "RegionSubRegion": "Asia",
    "Industry": "Services",
    "Year": 2020,
    "Ratio": 1.9,
    "Quartile1": 61.0,
    "Quartile2": 71.0,
    "Quartile3": 101.0,
    "Inapplicable_": [],
    "IsDeleted_": false,
    "StatusId_": 1,
    "CreatedBy_": "internalbatchuser",
    "CreatedDate_": "2020-09-03T09:25:03.110136Z",
    "t_": "ArcPeerQuartiles",
    "ContextUserId_": "internalbatchuser"
  }
]