[
  {
    "MapProfileSettingId": "2c2d29b2-d2d9-4c4d-a27e-a922232ea036",
    "FunctionalProfileSettingId": "70d20584-3252-4b5b-a6ed-26756db666b7",
    "EditMapConfiguration": true,
    "Inapplicable_": [],
    "WFId_": "00000000-0000-0000-0000-000000000000",
    "TaskId_": "00000000-0000-0000-0000-000000000000",
    "VersionId_": 8,
    "BaseVersionId_": 7,
    "IsLatestVersion_": true,
    "IsDeleted_": false,
    "StatusId_": 1,
    "CreatedBy_": "admin",
    "CreatedDate_": "2020-04-07T14:09:07.920718Z",
    "UpdatedBy_": "marian",
    "UpdatedDate_": "2020-09-25T13:22:13.26664Z",
    "t_": "MapProfileSetting",
    "ContextUserId_": "marian",
    "IsValid_": true,
    "IsVisible_": true,
    "SnapshotId_": 0
  }
]